feature_flag/core/__init__.py
feature_flag/core/base_repository.py
feature_flag/core/cache.py
feature_flag/core/decorators.py
feature_flag/models/__init__.py
feature_flag/models/feature_flag.py
feature_flag/repositories/__init__.py
feature_flag/repositories/postgres_repository.py
feature_flag/services/__init__.py
feature_flag/services/feature_flag_service.py
module_feature_flag-0.1.0.dist-info/LICENSE
module_feature_flag-0.1.0.dist-info/METADATA
module_feature_flag-0.1.0.dist-info/WHEEL
module_feature_flag-0.1.0.dist-info/RECORD
