Metadata-Version: 2.1
Name: module-feature-flag
Version: 0.1.0
Summary: A module for managing feature flags.
Author: Duc Duong
Author-email: duc.duong@c0x12c.com
Requires-Python: >=3.12,<4.0
Classifier: Programming Language :: Python :: 3
Classifier: Programming Language :: Python :: 3.12
Requires-Dist: inflection (>=0.5.1,<0.6.0)
Requires-Dist: orjson (>=3.10.7,<4.0.0)
Requires-Dist: psycopg2-binary (>=2.9.1,<3.0.0)
Requires-Dist: redis (>=5.0.8,<6.0.0)
Requires-Dist: sqlalchemy (>=2.0.32,<3.0.0)
